LICENSE
MANIFEST.in
README.md
setup.json
setup.py
aiida_cusp/__init__.py
aiida_cusp.egg-info/PKG-INFO
aiida_cusp.egg-info/SOURCES.txt
aiida_cusp.egg-info/dependency_links.txt
aiida_cusp.egg-info/entry_points.txt
aiida_cusp.egg-info/requires.txt
aiida_cusp.egg-info/top_level.txt
aiida_cusp/calculators/__init__.py
aiida_cusp/calculators/calculation_base.py
aiida_cusp/calculators/vasp_basic_calculation.py
aiida_cusp/calculators/vasp_calculation.py
aiida_cusp/calculators/vasp_neb_calculation.py
aiida_cusp/cli/__init__.py
aiida_cusp/cli/potcar_cmd.py
aiida_cusp/data/__init__.py
aiida_cusp/data/inputs/__init__.py
aiida_cusp/data/inputs/vasp_incar.py
aiida_cusp/data/inputs/vasp_kpoint.py
aiida_cusp/data/inputs/vasp_poscar.py
aiida_cusp/data/inputs/vasp_potcar.py
aiida_cusp/data/outputs/__init__.py
aiida_cusp/data/outputs/vasp_chgcar.py
aiida_cusp/data/outputs/vasp_contcar.py
aiida_cusp/data/outputs/vasp_generic.py
aiida_cusp/data/outputs/vasp_outcar.py
aiida_cusp/data/outputs/vasp_vasprun.py
aiida_cusp/data/outputs/vasp_wavecar.py
aiida_cusp/parsers/__init__.py
aiida_cusp/parsers/parser_base.py
aiida_cusp/parsers/vasp_file_parser.py
aiida_cusp/utils/__init__.py
aiida_cusp/utils/custodian.py
aiida_cusp/utils/decorators.py
aiida_cusp/utils/defaults.py
aiida_cusp/utils/exceptions.py
aiida_cusp/utils/potcar.py
aiida_cusp/utils/single_archive_data.py
tests/conftest.py
tests/calculators/basic_sub_calculation_test.py
tests/calculators/calculation_base_test.py
tests/calculators/neb_sub_calculation_test.py
tests/calculators/vasp_calculation_test.py
tests/data/inputs/incar_test.py
tests/data/inputs/kpoint_test.py
tests/data/inputs/poscar_test.py
tests/data/inputs/potcar_test.py
tests/data/outputs/outcar_test.py
tests/data/outputs/vasprun_test.py
tests/data/outputs/.testdata/OUTCAR
tests/data/outputs/.testdata/vasprun.xml
tests/parsers/parser_base_test.py
tests/parsers/vasp_file_parser_test.py
tests/utils/custodian_settings_test.py
tests/utils/potcar_utils_test.py
tests/utils/single_archive_data_test.py