Metadata-Version: 2.1
Name: aiida-cusp
Version: 0.1.0b2
Summary: Custodian based VASP Plugin for AiiDA
Home-page: https://github.com/astamminger/aiida-cusp
Author: Andreas Stamminger
Author-email: stammingera@gmail.com
License: MIT License
Platform: UNKNOWN
Classifier: Development Status :: 4 - Beta
Classifier: License :: OSI Approved :: MIT License
Classifier: Programming Language :: Python :: 3.6
Classifier: Programming Language :: Python :: 3.7
Classifier: Programming Language :: Python :: 3.8
Classifier: Topic :: Scientific/Engineering :: Physics
Classifier: Topic :: Scientific/Engineering :: Chemistry
Classifier: Environment :: Plugins
Classifier: Framework :: AiiDA
Provides-Extra: docs
Provides-Extra: develop
